README.md
setup.py
MyTT/MyTT.py
MyTT/MyTT_python2.py
MyTT/__init__.py
MyTT/example1.py
MyTT/hb_hq_api.py
MyTT.egg-info/PKG-INFO
MyTT.egg-info/SOURCES.txt
MyTT.egg-info/dependency_links.txt
MyTT.egg-info/requires.txt
MyTT.egg-info/top_level.txt