Metadata-Version: 1.0
Name: MyTT
Version: 2.9.3
Summary: Mini Python library with most stock market indicators
Home-page: https://github.com/mpquant/MyTT
Author: mpquant
Author-email: mpsoft163@163.com
License: MIT Licence
Keywords: pip,MyTT,indicators
Platform: any
